zoho_crm_connector/__init__.py
zoho_crm_connector/zoho_crm_api.py
zoho_crm_connector-1.0.3.dist-info/LICENCE.txt
zoho_crm_connector-1.0.3.dist-info/METADATA
zoho_crm_connector-1.0.3.dist-info/WHEEL
zoho_crm_connector-1.0.3.dist-info/top_level.txt
zoho_crm_connector-1.0.3.dist-info/RECORD
