Metadata-Version: 2.1
Name: zoho-crm-connector
Version: 1.0.3
Summary: Zoho CRM connector
Home-page: https://github.com/timrichardson/zoho_crm_package
Author: Tim Richardson
Author-email: tim@growthpath.com.au
License: MIT
Keywords: zoho crm
Classifier: Development Status :: 5 - Production/Stable
Classifier: License :: OSI Approved :: MIT License
Classifier: Programming Language :: Python :: 3.11
Classifier: Topic :: Internet :: WWW/HTTP
Requires-Python: >=3.6
License-File: LICENCE.txt
Requires-Dist: requests
